pycatchrs-0.0.1.dist-info/METADATA
pycatchrs-0.0.1.dist-info/WHEEL
pycatchrs-0.0.1.dist-info/licenses/LICENSE
pycatchrs/__init__.py
pycatchrs/pycatchrs.cpython-313t-aarch64-linux-gnu.so
pycatchrs-0.0.1.dist-info/RECORD
