Metadata-Version: 2.4
Name: pycatchrs
Version: 0.0.1
Classifier: Programming Language :: Python :: 3
Classifier: Operating System :: OS Independent
Requires-Dist: maturin
Requires-Dist: numpy
Requires-Dist: typeguard
License-File: LICENSE
Summary: pycatchrs is a "clone" of the original catch22 features(https://github.com/DynamicsAndNeuralSystems/catch22), providing an updated implementation with enhanced memory safety and significant improvements in computation speed. It uses a Rust backend for efficient and safe execution. 
Author-email: Alberto Azzari <alberto.azzari@univr.it>
Requires-Python: >=3.11
Project-URL: Homepage, https://github.com/albertoazzari/pycatch
Project-URL: Issues, https://github.com/albertoazzari/pycatch/issues
